textbook/chapter 4/ex1.vhdl
library ieee;
use ieee.std_logic_1164.all;

--entity
entity ex1 is
    port (
        A, B, C: in std_logic;
        F: out std_logic
    );
end ex1;

--architecture
architecture behave of ex1 is
begin
    F <= not (A and B and C);
end behave;

textbook/chapter 4/ex1_tb.vhdl
library ieee;
use ieee.std_logic_1164.all;

--entity
entity ex1_tb is
end ex1_tb;

--architecture
architecture test of ex1_tb is
    component ex1
        port (
            A, B, C: in std_logic;
            F: out std_logic
        );
    end component;

    signal A, B, C, F: std_logic;
begin
    exercise: ex1 port map (A => A, B => B, C => C, F => F);

    process begin
        A <= 'X';
        B <= 'X';
        C <= 'X';
        wait for 1 ns;

        A <= '0';
        B <= '0';
        C <= '0';
        wait for 1 ns;

        A <= '1';
        B <= '0';
        C <= '0';
        wait for 1 ns;

        A <= '0';
        B <= '1';
        C <= '0';
        wait for 1 ns;

        A <= '0';
        B <= '0';
        C <= '1';
        wait for 1 ns;

        A <= '1';
        B <= '1';
        C <= '0';
        wait for 1 ns;

        A <= '1';
        B <= '0';
        C <= '1';
        wait for 1 ns;

        A <= '0';
        B <= '1';
        C <= '1';
        wait for 1 ns;

        A <= '1';
        B <= '1';
        C <= '1';
        wait for 1 ns;

        assert false report "Reached end of test";
        wait;

    end process;
end test;

textbook/chapter 4/ex1.vcd
$date
  Wed Oct 14 23:46:44 2020
$end
$version
  GHDL v0
$end
$timescale
  1 fs
$end
$scope module standard $end
$upscope $end
$scope module std_logic_1164 $end
$upscope $end
$scope module ex1_tb $end
$var reg 1 ! a $end
$var reg 1 " b $end
$var reg 1 # c $end
$var reg 1 $ f $end
$scope module exercise $end
$var reg 1 % a $end
$var reg 1 & b $end
$var reg 1 ' c $end
$var reg 1 ( f $end
$upscope $end
$upscope $end
$enddefinitions $end
#0
X!
X"
X#
X$
X%
X&
X'
X(
#1000000
0!
0"
0#
1$
0%
0&
0'
1(
#2000000
1!
1%
#3000000
0!
1"
0%
1&
#4000000
0"
1#
0&
1'
#5000000
1!
1"
0#
1%
1&
0'
#6000000
0"
1#
0&
1'
#7000000
0!
1"
0%
1&
#8000000
1!
0$
1%
0(
