textbook/chapter 4/ex3.vhdl
library ieee;
use ieee.std_logic_1164.all;

entity ex3 is
    port (
        L, M, N: in std_logic;
        F3: out std_logic
    );
end ex3;

architecture behave of ex3 is
begin
    F3 <= 
        '1' when (L = '0' and M = '0' and N = '1') else
        '1' when (L = '1' and M = '1') else
        '0';            
end behave;

textbook/chapter 4/ex3_tb.vhdl
library ieee;
use ieee.std_logic_1164.all;

--entity
entity ex3_tb is
end ex3_tb;

--architecture
architecture test of ex3_tb is
    component ex3
        port (
            L, M, N: in std_logic;
            F3: out std_logic
        );
    end component;

    signal L, M, N, F3: std_logic;
begin
    exercise: ex3 port map (L => L, M => M, N => N, F3 => F3);

    process begin
        L <= 'X';
        M <= 'X';
        N <= 'X';
        wait for 1 ns;

        L <= '0';
        M <= '0';
        N <= '0';
        wait for 1 ns;

        L <= '1';
        M <= '0';
        N <= '0';
        wait for 1 ns;

        L <= '0';
        M <= '1';
        N <= '0';
        wait for 1 ns;

        L <= '0';
        M <= '0';
        N <= '1';
        wait for 1 ns;

        L <= '1';
        M <= '1';
        N <= '0';
        wait for 1 ns;

        L <= '1';
        M <= '0';
        N <= '1';
        wait for 1 ns;

        L <= '0';
        M <= '1';
        N <= '1';
        wait for 1 ns;

        L <= '1';
        M <= '1';
        N <= '1';
        wait for 1 ns;

        assert false report "Reached end of test";
        wait;

    end process;
end test;

textbook/chapter 4/ex3.vcd
$date
  Thu Oct 15 01:43:39 2020
$end
$version
  GHDL v0
$end
$timescale
  1 fs
$end
$scope module standard $end
$upscope $end
$scope module std_logic_1164 $end
$upscope $end
$scope module ex3_tb $end
$var reg 1 ! l $end
$var reg 1 " m $end
$var reg 1 # n $end
$var reg 1 $ f3 $end
$scope module exercise $end
$var reg 1 % l $end
$var reg 1 & m $end
$var reg 1 ' n $end
$var reg 1 ( f3 $end
$upscope $end
$upscope $end
$enddefinitions $end
#0
X!
X"
X#
0$
X%
X&
X'
0(
#1000000
0!
0"
0#
0%
0&
0'
#2000000
1!
1%
#3000000
0!
1"
0%
1&
#4000000
0"
1#
1$
0&
1'
1(
#5000000
1!
1"
0#
1%
1&
0'
#6000000
0"
1#
0$
0&
1'
0(
#7000000
0!
1"
0%
1&
#8000000
1!
1$
1%
1(
